[
 {
   "localityId": 100001,
   "regionId": "NG-AB",
   "localityName": "Aba North"
 },
 {
   "localityId": 100002,
   "regionId": "NG-AB",
   "localityName": "Aba South"
 },
 {
   "localityId": 100003,
   "regionId": "NG-AB",
   "localityName": "Arochukwu"
 },
 {
   "localityId": 100004,
   "regionId": "NG-AB",
   "localityName": "Bende"
 },
 {
   "localityId": 100005,
   "regionId": "NG-AB",
   "localityName": "Ikwuano"
 },
 {
   "localityId": 100006,
   "regionId": "NG-AB",
   "localityName": "Isiala-Ngwa North"
 },
 {
   "localityId": 100007,
   "regionId": "NG-AB",
   "localityName": "Isiala-Ngwa South"
 },
 {
   "localityId": 100008,
   "regionId": "NG-AB",
   "localityName": "Isuikwuato"
 },
 {
   "localityId": 100009,
   "regionId": "NG-AB",
   "localityName": "Obi Ngwa"
 },
 {
   "localityId": 100010,
   "regionId": "NG-AB",
   "localityName": "Ohafia"
 },
 {
   "localityId": 100011,
   "regionId": "NG-AB",
   "localityName": "Osisioma Ngwa"
 },
 {
   "localityId": 100012,
   "regionId": "NG-AB",
   "localityName": "Ugwunagbo"
 },
 {
   "localityId": 100013,
   "regionId": "NG-AB",
   "localityName": "Ukwa East"
 },
 {
   "localityId": 100014,
   "regionId": "NG-AB",
   "localityName": "Ukwa West"
 },
 {
   "localityId": 100015,
   "regionId": "NG-AB",
   "localityName": "Umuahia North"
 },
 {
   "localityId": 100016,
   "regionId": "NG-AB",
   "localityName": "Umuahia South"
 },
 {
   "localityId": 100017,
   "regionId": "NG-AB",
   "localityName": "Umu-Nneochi"
 },
 {
   "localityId": 100018,
   "regionId": "NG-AD",
   "localityName": "Demsa"
 },
 {
   "localityId": 100019,
   "regionId": "NG-AD",
   "localityName": "Fufore"
 },
 {
   "localityId": 100020,
   "regionId": "NG-AD",
   "localityName": "Ganye"
 },
 {
   "localityId": 100021,
   "regionId": "NG-AD",
   "localityName": "Girei"
 },
 {
   "localityId": 100022,
   "regionId": "NG-AD",
   "localityName": "Gombi"
 },
 {
   "localityId": 100023,
   "regionId": "NG-AD",
   "localityName": "Guyuk"
 },
 {
   "localityId": 100024,
   "regionId": "NG-AD",
   "localityName": "Hong"
 },
 {
   "localityId": 100025,
   "regionId": "NG-AD",
   "localityName": "Jada"
 },
 {
   "localityId": 100026,
   "regionId": "NG-AD",
   "localityName": "Lamurde"
 },
 {
   "localityId": 100027,
   "regionId": "NG-AD",
   "localityName": "Madagali"
 },
 {
   "localityId": 100028,
   "regionId": "NG-AD",
   "localityName": "Maiha"
 },
 {
   "localityId": 100029,
   "regionId": "NG-AD",
   "localityName": "Mayo-Belwa"
 },
 {
   "localityId": 100030,
   "regionId": "NG-AD",
   "localityName": "Michika"
 },
 {
   "localityId": 100031,
   "regionId": "NG-AD",
   "localityName": "Mubi North"
 },
 {
   "localityId": 100032,
   "regionId": "NG-AD",
   "localityName": "Mubi South"
 },
 {
   "localityId": 100033,
   "regionId": "NG-AD",
   "localityName": "Numan"
 },
 {
   "localityId": 100034,
   "regionId": "NG-AD",
   "localityName": "Shelleng"
 },
 {
   "localityId": 100035,
   "regionId": "NG-AD",
   "localityName": "Song"
 },
 {
   "localityId": 100036,
   "regionId": "NG-AD",
   "localityName": "Toungo"
 },
 {
   "localityId": 100037,
   "regionId": "NG-AD",
   "localityName": "Yola North"
 },
 {
   "localityId": 100038,
   "regionId": "NG-AD",
   "localityName": "Yola South"
 },
 {
   "localityId": 100039,
   "regionId": "NG-AK",
   "localityName": "Abak"
 },
 {
   "localityId": 100040,
   "regionId": "NG-AK",
   "localityName": "Eastern Obolo"
 },
 {
   "localityId": 100041,
   "regionId": "NG-AK",
   "localityName": "Eket"
 },
 {
   "localityId": 100042,
   "regionId": "NG-AK",
   "localityName": "Esit Eket"
 },
 {
   "localityId": 100043,
   "regionId": "NG-AK",
   "localityName": "Essien Udim"
 },
 {
   "localityId": 100044,
   "regionId": "NG-AK",
   "localityName": "Etim Ekpo"
 },
 {
   "localityId": 100045,
   "regionId": "NG-AK",
   "localityName": "Etinan"
 },
 {
   "localityId": 100046,
   "regionId": "NG-AK",
   "localityName": "Ibeno"
 },
 {
   "localityId": 100047,
   "regionId": "NG-AK",
   "localityName": "Ibesikpo Asutan"
 },
 {
   "localityId": 100048,
   "regionId": "NG-AK",
   "localityName": "Ibiono Ibom"
 },
 {
   "localityId": 100049,
   "regionId": "NG-AK",
   "localityName": "Ika"
 },
 {
   "localityId": 100050,
   "regionId": "NG-AK",
   "localityName": "Ikono"
 },
 {
   "localityId": 100051,
   "regionId": "NG-AK",
   "localityName": "Ikot Abasi"
 },
 {
   "localityId": 100052,
   "regionId": "NG-AK",
   "localityName": "Ikot Ekpene"
 },
 {
   "localityId": 100053,
   "regionId": "NG-AK",
   "localityName": "Ini"
 },
 {
   "localityId": 100054,
   "regionId": "NG-AK",
   "localityName": "Itu"
 },
 {
   "localityId": 100055,
   "regionId": "NG-AK",
   "localityName": "Mbo"
 },
 {
   "localityId": 100056,
   "regionId": "NG-AK",
   "localityName": "Mkpat Enin"
 },
 {
   "localityId": 100057,
   "regionId": "NG-AK",
   "localityName": "Nsit Atai"
 },
 {
   "localityId": 100058,
   "regionId": "NG-AK",
   "localityName": "Nsit Ibom"
 },
 {
   "localityId": 100059,
   "regionId": "NG-AK",
   "localityName": "Nsit Ubium"
 },
 {
   "localityId": 100060,
   "regionId": "NG-AK",
   "localityName": "Obot Akara"
 },
 {
   "localityId": 100061,
   "regionId": "NG-AK",
   "localityName": "Okobo"
 },
 {
   "localityId": 100062,
   "regionId": "NG-AK",
   "localityName": "Onna"
 },
 {
   "localityId": 100063,
   "regionId": "NG-AK",
   "localityName": "Oron"
 },
 {
   "localityId": 100064,
   "regionId": "NG-AK",
   "localityName": "Oruk Anam"
 },
 {
   "localityId": 100065,
   "regionId": "NG-AK",
   "localityName": "Udung Uko"
 },
 {
   "localityId": 100066,
   "regionId": "NG-AK",
   "localityName": "Ukanafun"
 },
 {
   "localityId": 100067,
   "regionId": "NG-AK",
   "localityName": "Uruan"
 },
 {
   "localityId": 100068,
   "regionId": "NG-AK",
   "localityName": "Urue-Offong/Oruko"
 },
 {
   "localityId": 100069,
   "regionId": "NG-AK",
   "localityName": "Uyo"
 },
 {
   "localityId": 100070,
   "regionId": "NG-AN",
   "localityName": "Aguata"
 },
 {
   "localityId": 100071,
   "regionId": "NG-AN",
   "localityName": "Anambra East"
 },
 {
   "localityId": 100072,
   "regionId": "NG-AN",
   "localityName": "Anambra West"
 },
 {
   "localityId": 100073,
   "regionId": "NG-AN",
   "localityName": "Anaocha"
 },
 {
   "localityId": 100074,
   "regionId": "NG-AN",
   "localityName": "Awka North"
 },
 {
   "localityId": 100075,
   "regionId": "NG-AN",
   "localityName": "Awka South"
 },
 {
   "localityId": 100076,
   "regionId": "NG-AN",
   "localityName": "Ayamelum"
 },
 {
   "localityId": 100077,
   "regionId": "NG-AN",
   "localityName": "Dunukofia"
 },
 {
   "localityId": 100078,
   "regionId": "NG-AN",
   "localityName": "Ekwusigo"
 },
 {
   "localityId": 100079,
   "regionId": "NG-AN",
   "localityName": "Idemili North"
 },
 {
   "localityId": 100080,
   "regionId": "NG-AN",
   "localityName": "Idemili South"
 },
 {
   "localityId": 100081,
   "regionId": "NG-AN",
   "localityName": "Ihiala"
 },
 {
   "localityId": 100082,
   "regionId": "NG-AN",
   "localityName": "Njikoka"
 },
 {
   "localityId": 100083,
   "regionId": "NG-AN",
   "localityName": "Nnewi North"
 },
 {
   "localityId": 100084,
   "regionId": "NG-AN",
   "localityName": "Nnewi South"
 },
 {
   "localityId": 100085,
   "regionId": "NG-AN",
   "localityName": "Ogbaru"
 },
 {
   "localityId": 100086,
   "regionId": "NG-AN",
   "localityName": "Onitsha North"
 },
 {
   "localityId": 100087,
   "regionId": "NG-AN",
   "localityName": "Onitsha South"
 },
 {
   "localityId": 100088,
   "regionId": "NG-AN",
   "localityName": "Orumba North"
 },
 {
   "localityId": 100089,
   "regionId": "NG-AN",
   "localityName": "Orumba South"
 },
 {
   "localityId": 100090,
   "regionId": "NG-AN",
   "localityName": "Oyi"
 },
 {
   "localityId": 100091,
   "regionId": "NG-BA",
   "localityName": "Alkaleri"
 },
 {
   "localityId": 100092,
   "regionId": "NG-BA",
   "localityName": "Bauchi"
 },
 {
   "localityId": 100093,
   "regionId": "NG-BA",
   "localityName": "Bogoro"
 },
 {
   "localityId": 100094,
   "regionId": "NG-BA",
   "localityName": "Damban"
 },
 {
   "localityId": 100095,
   "regionId": "NG-BA",
   "localityName": "Darazo"
 },
 {
   "localityId": 100096,
   "regionId": "NG-BA",
   "localityName": "Dass"
 },
 {
   "localityId": 100097,
   "regionId": "NG-BA",
   "localityName": "Gamawa"
 },
 {
   "localityId": 100098,
   "regionId": "NG-BA",
   "localityName": "Ganjuwa"
 },
 {
   "localityId": 100099,
   "regionId": "NG-BA",
   "localityName": "Giade"
 },
 {
   "localityId": 100100,
   "regionId": "NG-BA",
   "localityName": "Itas/Gadau"
 },
 {
   "localityId": 100101,
   "regionId": "NG-BA",
   "localityName": "Jama'are"
 },
 {
   "localityId": 100102,
   "regionId": "NG-BA",
   "localityName": "Katagum"
 },
 {
   "localityId": 100103,
   "regionId": "NG-BA",
   "localityName": "Kirfi"
 },
 {
   "localityId": 100104,
   "regionId": "NG-BA",
   "localityName": "Misau"
 },
 {
   "localityId": 100105,
   "regionId": "NG-BA",
   "localityName": "Ningi"
 },
 {
   "localityId": 100106,
   "regionId": "NG-BA",
   "localityName": "Shira"
 },
 {
   "localityId": 100107,
   "regionId": "NG-BA",
   "localityName": "Tafawa-Balewa"
 },
 {
   "localityId": 100108,
   "regionId": "NG-BA",
   "localityName": "Toro"
 },
 {
   "localityId": 100109,
   "regionId": "NG-BA",
   "localityName": "Warji"
 },
 {
   "localityId": 100110,
   "regionId": "NG-BA",
   "localityName": "Zaki"
 },
 {
   "localityId": 100111,
   "regionId": "NG-BY",
   "localityName": "Brass"
 },
 {
   "localityId": 100112,
   "regionId": "NG-BY",
   "localityName": "Ekeremor"
 },
 {
   "localityId": 100113,
   "regionId": "NG-BY",
   "localityName": "Kolokuma/Opokuma"
 },
 {
   "localityId": 100114,
   "regionId": "NG-BY",
   "localityName": "Nembe"
 },
 {
   "localityId": 100115,
   "regionId": "NG-BY",
   "localityName": "Ogbia"
 },
 {
   "localityId": 100116,
   "regionId": "NG-BY",
   "localityName": "Sagbama"
 },
 {
   "localityId": 100117,
   "regionId": "NG-BY",
   "localityName": "Southern Ijaw"
 },
 {
   "localityId": 100118,
   "regionId": "NG-BY",
   "localityName": "Yenagoa"
 },
 {
   "localityId": 100119,
   "regionId": "NG-BE",
   "localityName": "Ado"
 },
 {
   "localityId": 100120,
   "regionId": "NG-BE",
   "localityName": "Agatu"
 },
 {
   "localityId": 100121,
   "regionId": "NG-BE",
   "localityName": "Apa"
 },
 {
   "localityId": 100122,
   "regionId": "NG-BE",
   "localityName": "Buruku"
 },
 {
   "localityId": 100123,
   "regionId": "NG-BE",
   "localityName": "Gboko"
 },
 {
   "localityId": 100124,
   "regionId": "NG-BE",
   "localityName": "Guma"
 },
 {
   "localityId": 100125,
   "regionId": "NG-BE",
   "localityName": "Gwer East"
 },
 {
   "localityId": 100126,
   "regionId": "NG-BE",
   "localityName": "Gwer West"
 },
 {
   "localityId": 100127,
   "regionId": "NG-BE",
   "localityName": "Katsina-Ala"
 },
 {
   "localityId": 100128,
   "regionId": "NG-BE",
   "localityName": "Konshisha"
 },
 {
   "localityId": 100129,
   "regionId": "NG-BE",
   "localityName": "Kwande"
 },
 {
   "localityId": 100130,
   "regionId": "NG-BE",
   "localityName": "Logo"
 },
 {
   "localityId": 100131,
   "regionId": "NG-BE",
   "localityName": "Makurdi"
 },
 {
   "localityId": 100132,
   "regionId": "NG-BE",
   "localityName": "Obi"
 },
 {
   "localityId": 100133,
   "regionId": "NG-BE",
   "localityName": "Ogbadibo"
 },
 {
   "localityId": 100134,
   "regionId": "NG-BE",
   "localityName": "Ohimini"
 },
 {
   "localityId": 100135,
   "regionId": "NG-BE",
   "localityName": "Oju"
 },
 {
   "localityId": 100136,
   "regionId": "NG-BE",
   "localityName": "Okpokwu"
 },
 {
   "localityId": 100137,
   "regionId": "NG-BE",
   "localityName": "Oturkpo"
 },
 {
   "localityId": 100138,
   "regionId": "NG-BE",
   "localityName": "Tarka"
 },
 {
   "localityId": 100139,
   "regionId": "NG-BE",
   "localityName": "Ukum"
 },
 {
   "localityId": 100140,
   "regionId": "NG-BE",
   "localityName": "Ushongo"
 },
 {
   "localityId": 100141,
   "regionId": "NG-BE",
   "localityName": "Vandeikya"
 },
 {
   "localityId": 100142,
   "regionId": "NG-BO",
   "localityName": "Abadam"
 },
 {
   "localityId": 100143,
   "regionId": "NG-BO",
   "localityName": "Askira/Uba"
 },
 {
   "localityId": 100144,
   "regionId": "NG-BO",
   "localityName": "Bama"
 },
 {
   "localityId": 100145,
   "regionId": "NG-BO",
   "localityName": "Bayo"
 },
 {
   "localityId": 100146,
   "regionId": "NG-BO",
   "localityName": "Biu"
 },
 {
   "localityId": 100147,
   "regionId": "NG-BO",
   "localityName": "Chibok"
 },
 {
   "localityId": 100148,
   "regionId": "NG-BO",
   "localityName": "Damboa"
 },
 {
   "localityId": 100149,
   "regionId": "NG-BO",
   "localityName": "Dikwa"
 },
 {
   "localityId": 100150,
   "regionId": "NG-BO",
   "localityName": "Gubio"
 },
 {
   "localityId": 100151,
   "regionId": "NG-BO",
   "localityName": "Guzamala"
 },
 {
   "localityId": 100152,
   "regionId": "NG-BO",
   "localityName": "Gwoza"
 },
 {
   "localityId": 100153,
   "regionId": "NG-BO",
   "localityName": "Hawul"
 },
 {
   "localityId": 100154,
   "regionId": "NG-BO",
   "localityName": "Jere"
 },
 {
   "localityId": 100155,
   "regionId": "NG-BO",
   "localityName": "Kaga"
 },
 {
   "localityId": 100156,
   "regionId": "NG-BO",
   "localityName": "Kala/Balge"
 },
 {
   "localityId": 100157,
   "regionId": "NG-BO",
   "localityName": "Konduga"
 },
 {
   "localityId": 100158,
   "regionId": "NG-BO",
   "localityName": "Kukawa"
 },
 {
   "localityId": 100159,
   "regionId": "NG-BO",
   "localityName": "Kwaya Kusar"
 },
 {
   "localityId": 100160,
   "regionId": "NG-BO",
   "localityName": "Mafa"
 },
 {
   "localityId": 100161,
   "regionId": "NG-BO",
   "localityName": "Magumeri"
 },
 {
   "localityId": 100162,
   "regionId": "NG-BO",
   "localityName": "Maiduguri"
 },
 {
   "localityId": 100163,
   "regionId": "NG-BO",
   "localityName": "Marte"
 },
 {
   "localityId": 100164,
   "regionId": "NG-BO",
   "localityName": "Mobbar"
 },
 {
   "localityId": 100165,
   "regionId": "NG-BO",
   "localityName": "Monguno"
 },
 {
   "localityId": 100166,
   "regionId": "NG-BO",
   "localityName": "Ngala"
 },
 {
   "localityId": 100167,
   "regionId": "NG-BO",
   "localityName": "Nganzai"
 },
 {
   "localityId": 100168,
   "regionId": "NG-BO",
   "localityName": "Shani"
 },
 {
   "localityId": 100169,
   "regionId": "NG-CR",
   "localityName": "Abi"
 },
 {
   "localityId": 100170,
   "regionId": "NG-CR",
   "localityName": "Akamkpa"
 },
 {
   "localityId": 100171,
   "regionId": "NG-CR",
   "localityName": "Akpabuyo"
 },
 {
   "localityId": 100173,
   "regionId": "NG-CR",
   "localityName": "Bekwara"
 },
 {
   "localityId": 100174,
   "regionId": "NG-CR",
   "localityName": "Biase"
 },
 {
   "localityId": 100175,
   "regionId": "NG-CR",
   "localityName": "Boki"
 },
 {
   "localityId": 100176,
   "regionId": "NG-CR",
   "localityName": "Calabar Municipal"
 },
 {
   "localityId": 100177,
   "regionId": "NG-CR",
   "localityName": "Calabar South"
 },
 {
   "localityId": 100178,
   "regionId": "NG-CR",
   "localityName": "Etung"
 },
 {
   "localityId": 100179,
   "regionId": "NG-CR",
   "localityName": "Ikom"
 },
 {
   "localityId": 100180,
   "regionId": "NG-CR",
   "localityName": "Obanliku"
 },
 {
   "localityId": 100181,
   "regionId": "NG-CR",
   "localityName": "Obubra"
 },
 {
   "localityId": 100182,
   "regionId": "NG-CR",
   "localityName": "Obudu"
 },
 {
   "localityId": 100183,
   "regionId": "NG-CR",
   "localityName": "Odukpani"
 },
 {
   "localityId": 100184,
   "regionId": "NG-CR",
   "localityName": "Ogoja"
 },
 {
   "localityId": 100185,
   "regionId": "NG-CR",
   "localityName": "Yakurr"
 },
 {
   "localityId": 100186,
   "regionId": "NG-CR",
   "localityName": "Yala"
 },
 {
   "localityId": 100187,
   "regionId": "NG-DE",
   "localityName": "Aniocha North"
 },
 {
   "localityId": 100188,
   "regionId": "NG-DE",
   "localityName": "Aniocha South"
 },
 {
   "localityId": 100189,
   "regionId": "NG-DE",
   "localityName": "Bomadi"
 },
 {
   "localityId": 100190,
   "regionId": "NG-DE",
   "localityName": "Burutu"
 },
 {
   "localityId": 100191,
   "regionId": "NG-DE",
   "localityName": "Ethiope East"
 },
 {
   "localityId": 100192,
   "regionId": "NG-DE",
   "localityName": "Ethiope West"
 },
 {
   "localityId": 100193,
   "regionId": "NG-DE",
   "localityName": "Ika North East"
 },
 {
   "localityId": 100194,
   "regionId": "NG-DE",
   "localityName": "Ika South"
 },
 {
   "localityId": 100195,
   "regionId": "NG-DE",
   "localityName": "Isoko North"
 },
 {
   "localityId": 100196,
   "regionId": "NG-DE",
   "localityName": "Isoko South"
 },
 {
   "localityId": 100197,
   "regionId": "NG-DE",
   "localityName": "Ndokwa East"
 },
 {
   "localityId": 100198,
   "regionId": "NG-DE",
   "localityName": "Ndokwa West"
 },
 {
   "localityId": 100199,
   "regionId": "NG-DE",
   "localityName": "Okpe"
 },
 {
   "localityId": 100200,
   "regionId": "NG-DE",
   "localityName": "Oshimili North"
 },
 {
   "localityId": 100201,
   "regionId": "NG-DE",
   "localityName": "Oshimili South"
 },
 {
   "localityId": 100202,
   "regionId": "NG-DE",
   "localityName": "Patani"
 },
 {
   "localityId": 100203,
   "regionId": "NG-DE",
   "localityName": "Sapele"
 },
 {
   "localityId": 100204,
   "regionId": "NG-DE",
   "localityName": "Udu"
 },
 {
   "localityId": 100205,
   "regionId": "NG-DE",
   "localityName": "Ughelli North"
 },
 {
   "localityId": 100206,
   "regionId": "NG-DE",
   "localityName": "Ughelli South"
 },
 {
   "localityId": 100207,
   "regionId": "NG-DE",
   "localityName": "Ukwuani"
 },
 {
   "localityId": 100208,
   "regionId": "NG-DE",
   "localityName": "Uvwie"
 },
 {
   "localityId": 100209,
   "regionId": "NG-DE",
   "localityName": "Warri North"
 },
 {
   "localityId": 100210,
   "regionId": "NG-DE",
   "localityName": "Warri South"
 },
 {
   "localityId": 100211,
   "regionId": "NG-DE",
   "localityName": "Warri South West"
 },
 {
   "localityId": 100212,
   "regionId": "NG-EB",
   "localityName": "Abakaliki"
 },
 {
   "localityId": 100213,
   "regionId": "NG-EB",
   "localityName": "Afikpo North"
 },
 {
   "localityId": 100214,
   "regionId": "NG-EB",
   "localityName": "Afikpo South"
 },
 {
   "localityId": 100215,
   "regionId": "NG-EB",
   "localityName": "Ebonyi"
 },
 {
   "localityId": 100216,
   "regionId": "NG-EB",
   "localityName": "Ezza North"
 },
 {
   "localityId": 100217,
   "regionId": "NG-EB",
   "localityName": "Ezza South"
 },
 {
   "localityId": 100218,
   "regionId": "NG-EB",
   "localityName": "Ikwo"
 },
 {
   "localityId": 100219,
   "regionId": "NG-EB",
   "localityName": "Ishielu"
 },
 {
   "localityId": 100220,
   "regionId": "NG-EB",
   "localityName": "Ivo"
 },
 {
   "localityId": 100221,
   "regionId": "NG-EB",
   "localityName": "Izzi"
 },
 {
   "localityId": 100222,
   "regionId": "NG-EB",
   "localityName": "Ohaozara"
 },
 {
   "localityId": 100223,
   "regionId": "NG-EB",
   "localityName": "Ohaukwu"
 },
 {
   "localityId": 100224,
   "regionId": "NG-EB",
   "localityName": "Onicha"
 },
 {
   "localityId": 100225,
   "regionId": "NG-ED",
   "localityName": "Akoko-Edo"
 },
 {
   "localityId": 100226,
   "regionId": "NG-ED",
   "localityName": "Egor"
 },
 {
   "localityId": 100227,
   "regionId": "NG-ED",
   "localityName": "Esan Central"
 },
 {
   "localityId": 100228,
   "regionId": "NG-ED",
   "localityName": "Esan North East"
 },
 {
   "localityId": 100229,
   "regionId": "NG-ED",
   "localityName": "Esan South East"
 },
 {
   "localityId": 100230,
   "regionId": "NG-ED",
   "localityName": "Esan West"
 },
 {
   "localityId": 100231,
   "regionId": "NG-ED",
   "localityName": "Etsako Central"
 },
 {
   "localityId": 100232,
   "regionId": "NG-ED",
   "localityName": "Etsako East"
 },
 {
   "localityId": 100233,
   "regionId": "NG-ED",
   "localityName": "Etsako West"
 },
 {
   "localityId": 100234,
   "regionId": "NG-ED",
   "localityName": "Igueben"
 },
 {
   "localityId": 100235,
   "regionId": "NG-ED",
   "localityName": "Ikpoba-Okha"
 },
 {
   "localityId": 100236,
   "regionId": "NG-ED",
   "localityName": "Oredo"
 },
 {
   "localityId": 100237,
   "regionId": "NG-ED",
   "localityName": "Orhionmwon"
 },
 {
   "localityId": 100238,
   "regionId": "NG-ED",
   "localityName": "Ovia North East"
 },
 {
   "localityId": 100239,
   "regionId": "NG-ED",
   "localityName": "Ovia South West"
 },
 {
   "localityId": 100240,
   "regionId": "NG-ED",
   "localityName": "Owan East"
 },
 {
   "localityId": 100241,
   "regionId": "NG-ED",
   "localityName": "Owan West"
 },
 {
   "localityId": 100242,
   "regionId": "NG-ED",
   "localityName": "Uhunmwonde"
 },
 {
   "localityId": 100243,
   "regionId": "NG-EK",
   "localityName": "Ado Ekiti"
 },
 {
   "localityId": 100244,
   "regionId": "NG-EK",
   "localityName": "Aiyekire (Gbonyin)"
 },
 {
   "localityId": 100245,
   "regionId": "NG-EK",
   "localityName": "Efon"
 },
 {
   "localityId": 100246,
   "regionId": "NG-EK",
   "localityName": "Ekiti East"
 },
 {
   "localityId": 100247,
   "regionId": "NG-EK",
   "localityName": "Ekiti South"
 },
 {
   "localityId": 100248,
   "regionId": "NG-EK",
   "localityName": "Ekiti West"
 },
 {
   "localityId": 100249,
   "regionId": "NG-EK",
   "localityName": "Emure"
 },
 {
   "localityId": 100250,
   "regionId": "NG-EK",
   "localityName": "Ido-Osi"
 },
 {
   "localityId": 100251,
   "regionId": "NG-EK",
   "localityName": "Ijero"
 },
 {
   "localityId": 100252,
   "regionId": "NG-EK",
   "localityName": "Ikere"
 },
 {
   "localityId": 100253,
   "regionId": "NG-EK",
   "localityName": "Ikole"
 },
 {
   "localityId": 100254,
   "regionId": "NG-EK",
   "localityName": "Ilejemeje"
 },
 {
   "localityId": 100255,
   "regionId": "NG-EK",
   "localityName": "Irepodun/Ifelodun"
 },
 {
   "localityId": 100256,
   "regionId": "NG-EK",
   "localityName": "Ise/Orun"
 },
 {
   "localityId": 100257,
   "regionId": "NG-EK",
   "localityName": "Moba"
 },
 {
   "localityId": 100258,
   "regionId": "NG-EK",
   "localityName": "Oye"
 },
 {
   "localityId": 100259,
   "regionId": "NG-EN",
   "localityName": "Aninri"
 },
 {
   "localityId": 100260,
   "regionId": "NG-EN",
   "localityName": "Awgu"
 },
 {
   "localityId": 100261,
   "regionId": "NG-EN",
   "localityName": "Enugu East"
 },
 {
   "localityId": 100262,
   "regionId": "NG-EN",
   "localityName": "Enugu North"
 },
 {
   "localityId": 100263,
   "regionId": "NG-EN",
   "localityName": "Enugu South"
 },
 {
   "localityId": 100264,
   "regionId": "NG-EN",
   "localityName": "Ezeagu"
 },
 {
   "localityId": 100265,
   "regionId": "NG-EN",
   "localityName": "Igbo-Etiti"
 },
 {
   "localityId": 100266,
   "regionId": "NG-EN",
   "localityName": "Igbo-Eze North"
 },
 {
   "localityId": 100267,
   "regionId": "NG-EN",
   "localityName": "Igbo-Eze South"
 },
 {
   "localityId": 100268,
   "regionId": "NG-EN",
   "localityName": "Isi-Uzo"
 },
 {
   "localityId": 100269,
   "regionId": "NG-EN",
   "localityName": "Nkanu East"
 },
 {
   "localityId": 100270,
   "regionId": "NG-EN",
   "localityName": "Nkanu West"
 },
 {
   "localityId": 100271,
   "regionId": "NG-EN",
   "localityName": "Nsukka"
 },
 {
   "localityId": 100272,
   "regionId": "NG-EN",
   "localityName": "Oji-River"
 },
 {
   "localityId": 100273,
   "regionId": "NG-EN",
   "localityName": "Udenu"
 },
 {
   "localityId": 100274,
   "regionId": "NG-EN",
   "localityName": "Udi"
 },
 {
   "localityId": 100275,
   "regionId": "NG-EN",
   "localityName": "Uzo-Uwani"
 },
 {
   "localityId": 100276,
   "regionId": "NG-FC",
   "localityName": "Abaji"
 },
 {
   "localityId": 100277,
   "regionId": "NG-FC",
   "localityName": "Abuja Municipal Area Council"
 },
 {
   "localityId": 100278,
   "regionId": "NG-FC",
   "localityName": "Bwari"
 },
 {
   "localityId": 100279,
   "regionId": "NG-FC",
   "localityName": "Gwagwalada"
 },
 {
   "localityId": 100280,
   "regionId": "NG-FC",
   "localityName": "Kuje"
 },
 {
   "localityId": 100281,
   "regionId": "NG-FC",
   "localityName": "Kwali"
 },
 {
   "localityId": 100282,
   "regionId": "NG-GO",
   "localityName": "Akko"
 },
 {
   "localityId": 100283,
   "regionId": "NG-GO",
   "localityName": "Balanga"
 },
 {
   "localityId": 100284,
   "regionId": "NG-GO",
   "localityName": "Billiri"
 },
 {
   "localityId": 100285,
   "regionId": "NG-GO",
   "localityName": "Dukku"
 },
 {
   "localityId": 100286,
   "regionId": "NG-GO",
   "localityName": "Funakaye"
 },
 {
   "localityId": 100287,
   "regionId": "NG-GO",
   "localityName": "Gombe"
 },
 {
   "localityId": 100288,
   "regionId": "NG-GO",
   "localityName": "Kaltungo"
 },
 {
   "localityId": 100289,
   "regionId": "NG-GO",
   "localityName": "Kwami"
 },
 {
   "localityId": 100290,
   "regionId": "NG-GO",
   "localityName": "Nafada"
 },
 {
   "localityId": 100291,
   "regionId": "NG-GO",
   "localityName": "Shomgom"
 },
 {
   "localityId": 100292,
   "regionId": "NG-GO",
   "localityName": "Yamaltu/Deba"
 },
 {
   "localityId": 100293,
   "regionId": "NG-IM",
   "localityName": "Abo-Mbaise"
 },
 {
   "localityId": 100294,
   "regionId": "NG-IM",
   "localityName": "Ahiazu-Mbaise"
 },
 {
   "localityId": 100295,
   "regionId": "NG-IM",
   "localityName": "Ehime-Mbano"
 },
 {
   "localityId": 100296,
   "regionId": "NG-IM",
   "localityName": "Ezinihitte"
 },
 {
   "localityId": 100297,
   "regionId": "NG-IM",
   "localityName": "Ideato North"
 },
 {
   "localityId": 100298,
   "regionId": "NG-IM",
   "localityName": "Ideato South"
 },
 {
   "localityId": 100299,
   "regionId": "NG-IM",
   "localityName": "Ihitte/Uboma"
 },
 {
   "localityId": 100300,
   "regionId": "NG-IM",
   "localityName": "Ikeduru"
 },
 {
   "localityId": 100301,
   "regionId": "NG-IM",
   "localityName": "Isiala-Mbano"
 },
 {
   "localityId": 100302,
   "regionId": "NG-IM",
   "localityName": "Isu"
 },
 {
   "localityId": 100303,
   "regionId": "NG-IM",
   "localityName": "Mbaitoli"
 },
 {
   "localityId": 100304,
   "regionId": "NG-IM",
   "localityName": "Ngor-Okpala"
 },
 {
   "localityId": 100305,
   "regionId": "NG-IM",
   "localityName": "Njaba"
 },
 {
   "localityId": 100306,
   "regionId": "NG-IM",
   "localityName": "Nkwerre"
 },
 {
   "localityId": 100307,
   "regionId": "NG-IM",
   "localityName": "Nwangele"
 },
 {
   "localityId": 100308,
   "regionId": "NG-IM",
   "localityName": "Obowo"
 },
 {
   "localityId": 100309,
   "regionId": "NG-IM",
   "localityName": "Oguta"
 },
 {
   "localityId": 100310,
   "regionId": "NG-IM",
   "localityName": "Ohaji/Egbema"
 },
 {
   "localityId": 100311,
   "regionId": "NG-IM",
   "localityName": "Okigwe"
 },
 {
   "localityId": 100312,
   "regionId": "NG-IM",
   "localityName": "Orlu"
 },
 {
   "localityId": 100313,
   "regionId": "NG-IM",
   "localityName": "Orsu"
 },
 {
   "localityId": 100314,
   "regionId": "NG-IM",
   "localityName": "Oru East"
 },
 {
   "localityId": 100315,
   "regionId": "NG-IM",
   "localityName": "Oru West"
 },
 {
   "localityId": 100316,
   "regionId": "NG-IM",
   "localityName": "Owerri Municipal"
 },
 {
   "localityId": 100317,
   "regionId": "NG-IM",
   "localityName": "Owerri North"
 },
 {
   "localityId": 100318,
   "regionId": "NG-IM",
   "localityName": "Owerri West"
 },
 {
   "localityId": 100319,
   "regionId": "NG-IM",
   "localityName": "Unuimo"
 },
 {
   "localityId": 100320,
   "regionId": "NG-JI",
   "localityName": "Auyo"
 },
 {
   "localityId": 100321,
   "regionId": "NG-JI",
   "localityName": "Babura"
 },
 {
   "localityId": 100322,
   "regionId": "NG-JI",
   "localityName": "Biriniwa"
 },
 {
   "localityId": 100323,
   "regionId": "NG-JI",
   "localityName": "Birnin Kudu"
 },
 {
   "localityId": 100324,
   "regionId": "NG-JI",
   "localityName": "Buji"
 },
 {
   "localityId": 100325,
   "regionId": "NG-JI",
   "localityName": "Dutse"
 },
 {
   "localityId": 100326,
   "regionId": "NG-JI",
   "localityName": "Gagarawa"
 },
 {
   "localityId": 100327,
   "regionId": "NG-JI",
   "localityName": "Garki"
 },
 {
   "localityId": 100328,
   "regionId": "NG-JI",
   "localityName": "Gumel"
 },
 {
   "localityId": 100329,
   "regionId": "NG-JI",
   "localityName": "Guri"
 },
 {
   "localityId": 100330,
   "regionId": "NG-JI",
   "localityName": "Gwaram"
 },
 {
   "localityId": 100331,
   "regionId": "NG-JI",
   "localityName": "Gwiwa"
 },
 {
   "localityId": 100332,
   "regionId": "NG-JI",
   "localityName": "Hadejia"
 },
 {
   "localityId": 100333,
   "regionId": "NG-JI",
   "localityName": "Jahun"
 },
 {
   "localityId": 100334,
   "regionId": "NG-JI",
   "localityName": "Kafin Hausa"
 },
 {
   "localityId": 100335,
   "regionId": "NG-JI",
   "localityName": "Kaugama"
 },
 {
   "localityId": 100336,
   "regionId": "NG-JI",
   "localityName": "Kazaure"
 },
 {
   "localityId": 100337,
   "regionId": "NG-JI",
   "localityName": "Kiri Kasama"
 },
 {
   "localityId": 100338,
   "regionId": "NG-JI",
   "localityName": "Kiyawa"
 },
 {
   "localityId": 100339,
   "regionId": "NG-JI",
   "localityName": "Maigatari"
 },
 {
   "localityId": 100340,
   "regionId": "NG-JI",
   "localityName": "Malam Madori"
 },
 {
   "localityId": 100341,
   "regionId": "NG-JI",
   "localityName": "Miga"
 },
 {
   "localityId": 100342,
   "regionId": "NG-JI",
   "localityName": "Ringim"
 },
 {
   "localityId": 100343,
   "regionId": "NG-JI",
   "localityName": "Roni"
 },
 {
   "localityId": 100344,
   "regionId": "NG-JI",
   "localityName": "Sule Tankarkar"
 },
 {
   "localityId": 100345,
   "regionId": "NG-JI",
   "localityName": "Taura"
 },
 {
   "localityId": 100346,
   "regionId": "NG-JI",
   "localityName": "Yankwashi"
 },
 {
   "localityId": 100347,
   "regionId": "NG-KD",
   "localityName": "Birnin-Gwari"
 },
 {
   "localityId": 100348,
   "regionId": "NG-KD",
   "localityName": "Chikun"
 },
 {
   "localityId": 100349,
   "regionId": "NG-KD",
   "localityName": "Giwa"
 },
 {
   "localityId": 100350,
   "regionId": "NG-KD",
   "localityName": "Igabi"
 },
 {
   "localityId": 100351,
   "regionId": "NG-KD",
   "localityName": "Ikara"
 },
 {
   "localityId": 100352,
   "regionId": "NG-KD",
   "localityName": "Jaba"
 },
 {
   "localityId": 100353,
   "regionId": "NG-KD",
   "localityName": "Jema'a"
 },
 {
   "localityId": 100354,
   "regionId": "NG-KD",
   "localityName": "Kachia"
 },
 {
   "localityId": 100355,
   "regionId": "NG-KD",
   "localityName": "Kaduna North"
 },
 {
   "localityId": 100356,
   "regionId": "NG-KD",
   "localityName": "Kaduna South"
 },
 {
   "localityId": 100357,
   "regionId": "NG-KD",
   "localityName": "Kagarko"
 },
 {
   "localityId": 100358,
   "regionId": "NG-KD",
   "localityName": "Kajuru"
 },
 {
   "localityId": 100359,
   "regionId": "NG-KD",
   "localityName": "Kaura"
 },
 {
   "localityId": 100360,
   "regionId": "NG-KD",
   "localityName": "Kauru"
 },
 {
   "localityId": 100361,
   "regionId": "NG-KD",
   "localityName": "Kubau"
 },
 {
   "localityId": 100362,
   "regionId": "NG-KD",
   "localityName": "Kudan"
 },
 {
   "localityId": 100363,
   "regionId": "NG-KD",
   "localityName": "Lere"
 },
 {
   "localityId": 100364,
   "regionId": "NG-KD",
   "localityName": "Makarfi"
 },
 {
   "localityId": 100365,
   "regionId": "NG-KD",
   "localityName": "Sabon-Gari"
 },
 {
   "localityId": 100366,
   "regionId": "NG-KD",
   "localityName": "Sanga"
 },
 {
   "localityId": 100367,
   "regionId": "NG-KD",
   "localityName": "Soba"
 },
 {
   "localityId": 100368,
   "regionId": "NG-KD",
   "localityName": "Zangon-Kataf"
 },
 {
   "localityId": 100369,
   "regionId": "NG-KD",
   "localityName": "Zaria"
 },
 {
   "localityId": 100370,
   "regionId": "NG-KN",
   "localityName": "Ajingi"
 },
 {
   "localityId": 100371,
   "regionId": "NG-KN",
   "localityName": "Albasu"
 },
 {
   "localityId": 100372,
   "regionId": "NG-KN",
   "localityName": "Bagwai"
 },
 {
   "localityId": 100373,
   "regionId": "NG-KN",
   "localityName": "Bebeji"
 },
 {
   "localityId": 100374,
   "regionId": "NG-KN",
   "localityName": "Bichi"
 },
 {
   "localityId": 100375,
   "regionId": "NG-KN",
   "localityName": "Bunkure"
 },
 {
   "localityId": 100376,
   "regionId": "NG-KN",
   "localityName": "Dala"
 },
 {
   "localityId": 100377,
   "regionId": "NG-KN",
   "localityName": "Dambatta"
 },
 {
   "localityId": 100378,
   "regionId": "NG-KN",
   "localityName": "Dawakin Kudu"
 },
 {
   "localityId": 100379,
   "regionId": "NG-KN",
   "localityName": "Dawakin Tofa"
 },
 {
   "localityId": 100380,
   "regionId": "NG-KN",
   "localityName": "Doguwa"
 },
 {
   "localityId": 100381,
   "regionId": "NG-KN",
   "localityName": "Fagge"
 },
 {
   "localityId": 100382,
   "regionId": "NG-KN",
   "localityName": "Gabasawa"
 },
 {
   "localityId": 100383,
   "regionId": "NG-KN",
   "localityName": "Garko"
 },
 {
   "localityId": 100384,
   "regionId": "NG-KN",
   "localityName": "Garum Mallam"
 },
 {
   "localityId": 100385,
   "regionId": "NG-KN",
   "localityName": "Gaya"
 },
 {
   "localityId": 100386,
   "regionId": "NG-KN",
   "localityName": "Gezawa"
 },
 {
   "localityId": 100387,
   "regionId": "NG-KN",
   "localityName": "Gwale"
 },
 {
   "localityId": 100388,
   "regionId": "NG-KN",
   "localityName": "Gwarzo"
 },
 {
   "localityId": 100389,
   "regionId": "NG-KN",
   "localityName": "Kabo"
 },
 {
   "localityId": 100390,
   "regionId": "NG-KN",
   "localityName": "Kano Municipal"
 },
 {
   "localityId": 100391,
   "regionId": "NG-KN",
   "localityName": "Karaye"
 },
 {
   "localityId": 100392,
   "regionId": "NG-KN",
   "localityName": "Kibiya"
 },
 {
   "localityId": 100393,
   "regionId": "NG-KN",
   "localityName": "Kiru"
 },
 {
   "localityId": 100394,
   "regionId": "NG-KN",
   "localityName": "Kumbotso"
 },
 {
   "localityId": 100395,
   "regionId": "NG-KN",
   "localityName": "Kunchi"
 },
 {
   "localityId": 100396,
   "regionId": "NG-KN",
   "localityName": "Kura"
 },
 {
   "localityId": 100397,
   "regionId": "NG-KN",
   "localityName": "Madobi"
 },
 {
   "localityId": 100398,
   "regionId": "NG-KN",
   "localityName": "Makoda"
 },
 {
   "localityId": 100399,
   "regionId": "NG-KN",
   "localityName": "Minjibir"
 },
 {
   "localityId": 100400,
   "regionId": "NG-KN",
   "localityName": "Nasarawa"
 },
 {
   "localityId": 100401,
   "regionId": "NG-KN",
   "localityName": "Rano"
 },
 {
   "localityId": 100402,
   "regionId": "NG-KN",
   "localityName": "Rimin Gado"
 },
 {
   "localityId": 100403,
   "regionId": "NG-KN",
   "localityName": "Rogo"
 },
 {
   "localityId": 100404,
   "regionId": "NG-KN",
   "localityName": "Shanono"
 },
 {
   "localityId": 100405,
   "regionId": "NG-KN",
   "localityName": "Sumaila"
 },
 {
   "localityId": 100406,
   "regionId": "NG-KN",
   "localityName": "Takai"
 },
 {
   "localityId": 100407,
   "regionId": "NG-KN",
   "localityName": "Tarauni"
 },
 {
   "localityId": 100408,
   "regionId": "NG-KN",
   "localityName": "Tofa"
 },
 {
   "localityId": 100409,
   "regionId": "NG-KN",
   "localityName": "Tsanyawa"
 },
 {
   "localityId": 100410,
   "regionId": "NG-KN",
   "localityName": "Tudun Wada"
 },
 {
   "localityId": 100411,
   "regionId": "NG-KN",
   "localityName": "Ungogo"
 },
 {
   "localityId": 100412,
   "regionId": "NG-KN",
   "localityName": "Warawa"
 },
 {
   "localityId": 100413,
   "regionId": "NG-KN",
   "localityName": "Wudil"
 },
 {
   "localityId": 100414,
   "regionId": "NG-KT",
   "localityName": "Bakori"
 },
 {
   "localityId": 100415,
   "regionId": "NG-KT",
   "localityName": "Batagarawa"
 },
 {
   "localityId": 100416,
   "regionId": "NG-KT",
   "localityName": "Batsari"
 },
 {
   "localityId": 100417,
   "regionId": "NG-KT",
   "localityName": "Baure"
 },
 {
   "localityId": 100418,
   "regionId": "NG-KT",
   "localityName": "Bindawa"
 },
 {
   "localityId": 100419,
   "regionId": "NG-KT",
   "localityName": "Charanchi"
 },
 {
   "localityId": 100420,
   "regionId": "NG-KT",
   "localityName": "Dandume"
 },
 {
   "localityId": 100421,
   "regionId": "NG-KT",
   "localityName": "Danja"
 },
 {
   "localityId": 100422,
   "regionId": "NG-KT",
   "localityName": "Dan Musa"
 },
 {
   "localityId": 100423,
   "regionId": "NG-KT",
   "localityName": "Daura"
 },
 {
   "localityId": 100424,
   "regionId": "NG-KT",
   "localityName": "Dutsi"
 },
 {
   "localityId": 100425,
   "regionId": "NG-KT",
   "localityName": "Dutsin-Ma"
 },
 {
   "localityId": 100426,
   "regionId": "NG-KT",
   "localityName": "Faskari"
 },
 {
   "localityId": 100427,
   "regionId": "NG-KT",
   "localityName": "Funtua"
 },
 {
   "localityId": 100428,
   "regionId": "NG-KT",
   "localityName": "Ingawa"
 },
 {
   "localityId": 100429,
   "regionId": "NG-KT",
   "localityName": "Jibia"
 },
 {
   "localityId": 100430,
   "regionId": "NG-KT",
   "localityName": "Kafur"
 },
 {
   "localityId": 100431,
   "regionId": "NG-KT",
   "localityName": "Kaita"
 },
 {
   "localityId": 100432,
   "regionId": "NG-KT",
   "localityName": "Kankara"
 },
 {
   "localityId": 100433,
   "regionId": "NG-KT",
   "localityName": "Kankia"
 },
 {
   "localityId": 100434,
   "regionId": "NG-KT",
   "localityName": "Katsina"
 },
 {
   "localityId": 100435,
   "regionId": "NG-KT",
   "localityName": "Kurfi"
 },
 {
   "localityId": 100436,
   "regionId": "NG-KT",
   "localityName": "Kusada"
 },
 {
   "localityId": 100437,
   "regionId": "NG-KT",
   "localityName": "Mai'adua"
 },
 {
   "localityId": 100438,
   "regionId": "NG-KT",
   "localityName": "Malumfashi"
 },
 {
   "localityId": 100439,
   "regionId": "NG-KT",
   "localityName": "Mani"
 },
 {
   "localityId": 100440,
   "regionId": "NG-KT",
   "localityName": "Mashi"
 },
 {
   "localityId": 100441,
   "regionId": "NG-KT",
   "localityName": "Matazu"
 },
 {
   "localityId": 100442,
   "regionId": "NG-KT",
   "localityName": "Musawa"
 },
 {
   "localityId": 100443,
   "regionId": "NG-KT",
   "localityName": "Rimi"
 },
 {
   "localityId": 100444,
   "regionId": "NG-KT",
   "localityName": "Sabuwa"
 },
 {
   "localityId": 100445,
   "regionId": "NG-KT",
   "localityName": "Safana"
 },
 {
   "localityId": 100446,
   "regionId": "NG-KT",
   "localityName": "Sandamu"
 },
 {
   "localityId": 100447,
   "regionId": "NG-KT",
   "localityName": "Zango"
 },
 {
   "localityId": 100448,
   "regionId": "NG-KE",
   "localityName": "Aleiro"
 },
 {
   "localityId": 100449,
   "regionId": "NG-KE",
   "localityName": "Arewa-Dandi"
 },
 {
   "localityId": 100450,
   "regionId": "NG-KE",
   "localityName": "Argungu"
 },
 {
   "localityId": 100451,
   "regionId": "NG-KE",
   "localityName": "Augie"
 },
 {
   "localityId": 100452,
   "regionId": "NG-KE",
   "localityName": "Bagudo"
 },
 {
   "localityId": 100453,
   "regionId": "NG-KE",
   "localityName": "Birnin Kebbi"
 },
 {
   "localityId": 100454,
   "regionId": "NG-KE",
   "localityName": "Bunza"
 },
 {
   "localityId": 100455,
   "regionId": "NG-KE",
   "localityName": "Dandi"
 },
 {
   "localityId": 100456,
   "regionId": "NG-KE",
   "localityName": "Fakai"
 },
 {
   "localityId": 100457,
   "regionId": "NG-KE",
   "localityName": "Gwandu"
 },
 {
   "localityId": 100458,
   "regionId": "NG-KE",
   "localityName": "Jega"
 },
 {
   "localityId": 100459,
   "regionId": "NG-KE",
   "localityName": "Kalgo"
 },
 {
   "localityId": 100460,
   "regionId": "NG-KE",
   "localityName": "Koko/Besse"
 },
 {
   "localityId": 100461,
   "regionId": "NG-KE",
   "localityName": "Maiyama"
 },
 {
   "localityId": 100462,
   "regionId": "NG-KE",
   "localityName": "Ngaski"
 },
 {
   "localityId": 100463,
   "regionId": "NG-KE",
   "localityName": "Sakaba"
 },
 {
   "localityId": 100464,
   "regionId": "NG-KE",
   "localityName": "Shanga"
 },
 {
   "localityId": 100465,
   "regionId": "NG-KE",
   "localityName": "Suru"
 },
 {
   "localityId": 100466,
   "regionId": "NG-KE",
   "localityName": "Wasagu/Danko"
 },
 {
   "localityId": 100467,
   "regionId": "NG-KE",
   "localityName": "Yauri"
 },
 {
   "localityId": 100468,
   "regionId": "NG-KE",
   "localityName": "Zuru"
 },
 {
   "localityId": 100469,
   "regionId": "NG-KO",
   "localityName": "Adavi"
 },
 {
   "localityId": 100470,
   "regionId": "NG-KO",
   "localityName": "Ajaokuta"
 },
 {
   "localityId": 100471,
   "regionId": "NG-KO",
   "localityName": "Ankpa"
 },
 {
   "localityId": 100472,
   "regionId": "NG-KO",
   "localityName": "Bassa"
 },
 {
   "localityId": 100473,
   "regionId": "NG-KO",
   "localityName": "Dekina"
 },
 {
   "localityId": 100474,
   "regionId": "NG-KO",
   "localityName": "Ibaji"
 },
 {
   "localityId": 100475,
   "regionId": "NG-KO",
   "localityName": "Idah"
 },
 {
   "localityId": 100476,
   "regionId": "NG-KO",
   "localityName": "Igalamela-Odolu"
 },
 {
   "localityId": 100477,
   "regionId": "NG-KO",
   "localityName": "Ijumu"
 },
 {
   "localityId": 100478,
   "regionId": "NG-KO",
   "localityName": "Kabba/Bunu"
 },
 {
   "localityId": 100479,
   "regionId": "NG-KO",
   "localityName": "Kogi"
 },
 {
   "localityId": 100480,
   "regionId": "NG-KO",
   "localityName": "Lokoja"
 },
 {
   "localityId": 100481,
   "regionId": "NG-KO",
   "localityName": "Mopa-Muro"
 },
 {
   "localityId": 100482,
   "regionId": "NG-KO",
   "localityName": "Ofu"
 },
 {
   "localityId": 100483,
   "regionId": "NG-KO",
   "localityName": "Ogori/Magongo"
 },
 {
   "localityId": 100484,
   "regionId": "NG-KO",
   "localityName": "Okehi"
 },
 {
   "localityId": 100485,
   "regionId": "NG-KO",
   "localityName": "Okene"
 },
 {
   "localityId": 100486,
   "regionId": "NG-KO",
   "localityName": "Olamaboro"
 },
 {
   "localityId": 100487,
   "regionId": "NG-KO",
   "localityName": "Omala"
 },
 {
   "localityId": 100488,
   "regionId": "NG-KO",
   "localityName": "Yagba East"
 },
 {
   "localityId": 100489,
   "regionId": "NG-KO",
   "localityName": "Yagba West"
 },
 {
   "localityId": 100490,
   "regionId": "NG-KW",
   "localityName": "Asa"
 },
 {
   "localityId": 100491,
   "regionId": "NG-KW",
   "localityName": "Baruten"
 },
 {
   "localityId": 100492,
   "regionId": "NG-KW",
   "localityName": "Edu"
 },
 {
   "localityId": 100493,
   "regionId": "NG-KW",
   "localityName": "Ekiti"
 },
 {
   "localityId": 100494,
   "regionId": "NG-KW",
   "localityName": "Ifelodun"
 },
 {
   "localityId": 100495,
   "regionId": "NG-KW",
   "localityName": "Ilorin East"
 },
 {
   "localityId": 100496,
   "regionId": "NG-KW",
   "localityName": "Ilorin South"
 },
 {
   "localityId": 100497,
   "regionId": "NG-KW",
   "localityName": "Ilorin West"
 },
 {
   "localityId": 100498,
   "regionId": "NG-KW",
   "localityName": "Irepodun"
 },
 {
   "localityId": 100499,
   "regionId": "NG-KW",
   "localityName": "Isin"
 },
 {
   "localityId": 100500,
   "regionId": "NG-KW",
   "localityName": "Kaiama"
 },
 {
   "localityId": 100501,
   "regionId": "NG-KW",
   "localityName": "Moro"
 },
 {
   "localityId": 100502,
   "regionId": "NG-KW",
   "localityName": "Offa"
 },
 {
   "localityId": 100503,
   "regionId": "NG-KW",
   "localityName": "Oke-Ero"
 },
 {
   "localityId": 100504,
   "regionId": "NG-KW",
   "localityName": "Oyun"
 },
 {
   "localityId": 100505,
   "regionId": "NG-KW",
   "localityName": "Pategi"
 },
 {
   "localityId": 100506,
   "regionId": "NG-LA",
   "localityName": "Agege"
 },
 {
   "localityId": 100507,
   "regionId": "NG-LA",
   "localityName": "Ajeromi-Ifelodun"
 },
 {
   "localityId": 100508,
   "regionId": "NG-LA",
   "localityName": "Alimosho"
 },
 {
   "localityId": 100509,
   "regionId": "NG-LA",
   "localityName": "Amuwo-Odofin"
 },
 {
   "localityId": 100510,
   "regionId": "NG-LA",
   "localityName": "Apapa"
 },
 {
   "localityId": 100511,
   "regionId": "NG-LA",
   "localityName": "Badagry"
 },
 {
   "localityId": 100512,
   "regionId": "NG-LA",
   "localityName": "Epe"
 },
 {
   "localityId": 100513,
   "regionId": "NG-LA",
   "localityName": "Eti Osa"
 },
 {
   "localityId": 100514,
   "regionId": "NG-LA",
   "localityName": "Ibeju/Lekki"
 },
 {
   "localityId": 100515,
   "regionId": "NG-LA",
   "localityName": "Ifako-Ijaye"
 },
 {
   "localityId": 100516,
   "regionId": "NG-LA",
   "localityName": "Ikeja"
 },
 {
   "localityId": 100517,
   "regionId": "NG-LA",
   "localityName": "Ikorodu"
 },
 {
   "localityId": 100518,
   "regionId": "NG-LA",
   "localityName": "Kosofe"
 },
 {
   "localityId": 100519,
   "regionId": "NG-LA",
   "localityName": "Lagos Island"
 },
 {
   "localityId": 100520,
   "regionId": "NG-LA",
   "localityName": "Lagos Mainland"
 },
 {
   "localityId": 100521,
   "regionId": "NG-LA",
   "localityName": "Mushin"
 },
 {
   "localityId": 100522,
   "regionId": "NG-LA",
   "localityName": "Ojo"
 },
 {
   "localityId": 100523,
   "regionId": "NG-LA",
   "localityName": "Oshodi-Isolo"
 },
 {
   "localityId": 100524,
   "regionId": "NG-LA",
   "localityName": "Shomolu"
 },
 {
   "localityId": 100525,
   "regionId": "NG-LA",
   "localityName": "Surulere"
 },
 {
   "localityId": 100526,
   "regionId": "NG-NA",
   "localityName": "Akwanga"
 },
 {
   "localityId": 100527,
   "regionId": "NG-NA",
   "localityName": "Awe"
 },
 {
   "localityId": 100528,
   "regionId": "NG-NA",
   "localityName": "Doma"
 },
 {
   "localityId": 100529,
   "regionId": "NG-NA",
   "localityName": "Karu"
 },
 {
   "localityId": 100530,
   "regionId": "NG-NA",
   "localityName": "Keana"
 },
 {
   "localityId": 100531,
   "regionId": "NG-NA",
   "localityName": "Keffi"
 },
 {
   "localityId": 100532,
   "regionId": "NG-NA",
   "localityName": "Kokona"
 },
 {
   "localityId": 100533,
   "regionId": "NG-NA",
   "localityName": "Lafia"
 },
 {
   "localityId": 100534,
   "regionId": "NG-NA",
   "localityName": "Nasarawa"
 },
 {
   "localityId": 100535,
   "regionId": "NG-NA",
   "localityName": "Nasarawa-Eggon"
 },
 {
   "localityId": 100536,
   "regionId": "NG-NA",
   "localityName": "Obi"
 },
 {
   "localityId": 100537,
   "regionId": "NG-NA",
   "localityName": "Toto"
 },
 {
   "localityId": 100538,
   "regionId": "NG-NA",
   "localityName": "Wamba"
 },
 {
   "localityId": 100539,
   "regionId": "NG-NI",
   "localityName": "Agaie"
 },
 {
   "localityId": 100540,
   "regionId": "NG-NI",
   "localityName": "Agwara"
 },
 {
   "localityId": 100541,
   "regionId": "NG-NI",
   "localityName": "Bida"
 },
 {
   "localityId": 100542,
   "regionId": "NG-NI",
   "localityName": "Borgu"
 },
 {
   "localityId": 100543,
   "regionId": "NG-NI",
   "localityName": "Bosso"
 },
 {
   "localityId": 100544,
   "regionId": "NG-NI",
   "localityName": "Chanchaga"
 },
 {
   "localityId": 100545,
   "regionId": "NG-NI",
   "localityName": "Edati"
 },
 {
   "localityId": 100546,
   "regionId": "NG-NI",
   "localityName": "Gbako"
 },
 {
   "localityId": 100547,
   "regionId": "NG-NI",
   "localityName": "Gurara"
 },
 {
   "localityId": 100548,
   "regionId": "NG-NI",
   "localityName": "Katcha"
 },
 {
   "localityId": 100549,
   "regionId": "NG-NI",
   "localityName": "Kontagora"
 },
 {
   "localityId": 100550,
   "regionId": "NG-NI",
   "localityName": "Lapai"
 },
 {
   "localityId": 100551,
   "regionId": "NG-NI",
   "localityName": "Lavun"
 },
 {
   "localityId": 100552,
   "regionId": "NG-NI",
   "localityName": "Magama"
 },
 {
   "localityId": 100553,
   "regionId": "NG-NI",
   "localityName": "Mariga"
 },
 {
   "localityId": 100554,
   "regionId": "NG-NI",
   "localityName": "Mashegu"
 },
 {
   "localityId": 100555,
   "regionId": "NG-NI",
   "localityName": "Mokwa"
 },
 {
   "localityId": 100556,
   "regionId": "NG-NI",
   "localityName": "Muya"
 },
 {
   "localityId": 100557,
   "regionId": "NG-NI",
   "localityName": "Paikoro"
 },
 {
   "localityId": 100558,
   "regionId": "NG-NI",
   "localityName": "Rafi"
 },
 {
   "localityId": 100559,
   "regionId": "NG-NI",
   "localityName": "Rijau"
 },
 {
   "localityId": 100560,
   "regionId": "NG-NI",
   "localityName": "Shiroro"
 },
 {
   "localityId": 100561,
   "regionId": "NG-NI",
   "localityName": "Suleja"
 },
 {
   "localityId": 100562,
   "regionId": "NG-NI",
   "localityName": "Tafa"
 },
 {
   "localityId": 100563,
   "regionId": "NG-NI",
   "localityName": "Wushishi"
 },
 {
   "localityId": 100564,
   "regionId": "NG-OG",
   "localityName": "Abeokuta Nor"
 },
 {
   "localityId": 100565,
   "regionId": "NG-OG",
   "localityName": "Abeokuta Sou"
 },
 {
   "localityId": 100566,
   "regionId": "NG-OG",
   "localityName": "Ado-Odo/Ota"
 },
 {
   "localityId": 100567,
   "regionId": "NG-OG",
   "localityName": "Ewekoro"
 },
 {
   "localityId": 100568,
   "regionId": "NG-OG",
   "localityName": "Ifo"
 },
 {
   "localityId": 100569,
   "regionId": "NG-OG",
   "localityName": "Ijebu East"
 },
 {
   "localityId": 100570,
   "regionId": "NG-OG",
   "localityName": "Ijebu North"
 },
 {
   "localityId": 100571,
   "regionId": "NG-OG",
   "localityName": "Ijebu North East"
 },
 {
   "localityId": 100572,
   "regionId": "NG-OG",
   "localityName": "Ijebu Ode"
 },
 {
   "localityId": 100573,
   "regionId": "NG-OG",
   "localityName": "Ikenne"
 },
 {
   "localityId": 100574,
   "regionId": "NG-OG",
   "localityName": "Imeko Afon"
 },
 {
   "localityId": 100575,
   "regionId": "NG-OG",
   "localityName": "Ipokia"
 },
 {
   "localityId": 100576,
   "regionId": "NG-OG",
   "localityName": "Obafemi Owode"
 },
 {
   "localityId": 100577,
   "regionId": "NG-OG",
   "localityName": "Odeda"
 },
 {
   "localityId": 100578,
   "regionId": "NG-OG",
   "localityName": "Odogbolu"
 },
 {
   "localityId": 100579,
   "regionId": "NG-OG",
   "localityName": "Ogun Waterside"
 },
 {
   "localityId": 100580,
   "regionId": "NG-OG",
   "localityName": "Remo North"
 },
 {
   "localityId": 100581,
   "regionId": "NG-OG",
   "localityName": "Sagamu"
 },
 {
   "localityId": 100582,
   "regionId": "NG-OG",
   "localityName": "Yewa North (Egbado North)"
 },
 {
   "localityId": 100583,
   "regionId": "NG-OG",
   "localityName": "Yewa South (Egbado South)"
 },
 {
   "localityId": 100584,
   "regionId": "NG-ON",
   "localityName": "Akoko North East"
 },
 {
   "localityId": 100585,
   "regionId": "NG-ON",
   "localityName": "Akoko North West"
 },
 {
   "localityId": 100586,
   "regionId": "NG-ON",
   "localityName": "Akoko South East"
 },
 {
   "localityId": 100587,
   "regionId": "NG-ON",
   "localityName": "Akoko South West"
 },
 {
   "localityId": 100588,
   "regionId": "NG-ON",
   "localityName": "Akure North"
 },
 {
   "localityId": 100589,
   "regionId": "NG-ON",
   "localityName": "Akure South"
 },
 {
   "localityId": 100590,
   "regionId": "NG-ON",
   "localityName": "Ese-Odo"
 },
 {
   "localityId": 100591,
   "regionId": "NG-ON",
   "localityName": "Idanre"
 },
 {
   "localityId": 100592,
   "regionId": "NG-ON",
   "localityName": "Ifedore"
 },
 {
   "localityId": 100593,
   "regionId": "NG-ON",
   "localityName": "Ilaje"
 },
 {
   "localityId": 100594,
   "regionId": "NG-ON",
   "localityName": "Ile-Oluji-Okeigbo"
 },
 {
   "localityId": 100595,
   "regionId": "NG-ON",
   "localityName": "Irele"
 },
 {
   "localityId": 100596,
   "regionId": "NG-ON",
   "localityName": "Odigbo"
 },
 {
   "localityId": 100597,
   "regionId": "NG-ON",
   "localityName": "Okitipupa"
 },
 {
   "localityId": 100598,
   "regionId": "NG-ON",
   "localityName": "Ondo East"
 },
 {
   "localityId": 100599,
   "regionId": "NG-ON",
   "localityName": "Ondo West"
 },
 {
   "localityId": 100600,
   "regionId": "NG-ON",
   "localityName": "Ose"
 },
 {
   "localityId": 100601,
   "regionId": "NG-ON",
   "localityName": "Owo"
 },
 {
   "localityId": 100602,
   "regionId": "NG-OS",
   "localityName": "Aiyedaade"
 },
 {
   "localityId": 100603,
   "regionId": "NG-OS",
   "localityName": "Aiyedire"
 },
 {
   "localityId": 100604,
   "regionId": "NG-OS",
   "localityName": "Atakunmosa East"
 },
 {
   "localityId": 100605,
   "regionId": "NG-OS",
   "localityName": "Atakunmosa West"
 },
 {
   "localityId": 100606,
   "regionId": "NG-OS",
   "localityName": "Boluwaduro"
 },
 {
   "localityId": 100607,
   "regionId": "NG-OS",
   "localityName": "Boripe"
 },
 {
   "localityId": 100608,
   "regionId": "NG-OS",
   "localityName": "Ede North"
 },
 {
   "localityId": 100609,
   "regionId": "NG-OS",
   "localityName": "Ede South"
 },
 {
   "localityId": 100610,
   "regionId": "NG-OS",
   "localityName": "Egbedore"
 },
 {
   "localityId": 100611,
   "regionId": "NG-OS",
   "localityName": "Ejigbo"
 },
 {
   "localityId": 100612,
   "regionId": "NG-OS",
   "localityName": "Ife Central"
 },
 {
   "localityId": 100613,
   "regionId": "NG-OS",
   "localityName": "Ifedayo"
 },
 {
   "localityId": 100614,
   "regionId": "NG-OS",
   "localityName": "Ife East"
 },
 {
   "localityId": 100615,
   "regionId": "NG-OS",
   "localityName": "Ifelodun"
 },
 {
   "localityId": 100616,
   "regionId": "NG-OS",
   "localityName": "Ife North"
 },
 {
   "localityId": 100617,
   "regionId": "NG-OS",
   "localityName": "Ife South"
 },
 {
   "localityId": 100618,
   "regionId": "NG-OS",
   "localityName": "Ila"
 },
 {
   "localityId": 100619,
   "regionId": "NG-OS",
   "localityName": "Ilesha East"
 },
 {
   "localityId": 100620,
   "regionId": "NG-OS",
   "localityName": "Ilesha West"
 },
 {
   "localityId": 100621,
   "regionId": "NG-OS",
   "localityName": "Irepodun"
 },
 {
   "localityId": 100622,
   "regionId": "NG-OS",
   "localityName": "Irewole"
 },
 {
   "localityId": 100623,
   "regionId": "NG-OS",
   "localityName": "Isokan"
 },
 {
   "localityId": 100624,
   "regionId": "NG-OS",
   "localityName": "Iwo"
 },
 {
   "localityId": 100625,
   "regionId": "NG-OS",
   "localityName": "Obokun"
 },
 {
   "localityId": 100626,
   "regionId": "NG-OS",
   "localityName": "Odo-Otin"
 },
 {
   "localityId": 100627,
   "regionId": "NG-OS",
   "localityName": "Ola-Oluwa"
 },
 {
   "localityId": 100628,
   "regionId": "NG-OS",
   "localityName": "Olorunda"
 },
 {
   "localityId": 100629,
   "regionId": "NG-OS",
   "localityName": "Oriade"
 },
 {
   "localityId": 100630,
   "regionId": "NG-OS",
   "localityName": "Orolu"
 },
 {
   "localityId": 100631,
   "regionId": "NG-OS",
   "localityName": "Osogbo"
 },
 {
   "localityId": 100632,
   "regionId": "NG-OY",
   "localityName": "Afijio"
 },
 {
   "localityId": 100633,
   "regionId": "NG-OY",
   "localityName": "Akinyele"
 },
 {
   "localityId": 100634,
   "regionId": "NG-OY",
   "localityName": "Atiba"
 },
 {
   "localityId": 100635,
   "regionId": "NG-OY",
   "localityName": "Atisbo"
 },
 {
   "localityId": 100636,
   "regionId": "NG-OY",
   "localityName": "Egbeda"
 },
 {
   "localityId": 100637,
   "regionId": "NG-OY",
   "localityName": "Ibadan North"
 },
 {
   "localityId": 100638,
   "regionId": "NG-OY",
   "localityName": "Ibadan North East"
 },
 {
   "localityId": 100639,
   "regionId": "NG-OY",
   "localityName": "Ibadan North West"
 },
 {
   "localityId": 100640,
   "regionId": "NG-OY",
   "localityName": "Ibadan South East"
 },
 {
   "localityId": 100641,
   "regionId": "NG-OY",
   "localityName": "Ibadan South West"
 },
 {
   "localityId": 100642,
   "regionId": "NG-OY",
   "localityName": "Ibarapa Central"
 },
 {
   "localityId": 100643,
   "regionId": "NG-OY",
   "localityName": "Ibarapa East"
 },
 {
   "localityId": 100644,
   "regionId": "NG-OY",
   "localityName": "Ibarapa North"
 },
 {
   "localityId": 100645,
   "regionId": "NG-OY",
   "localityName": "Ido"
 },
 {
   "localityId": 100646,
   "regionId": "NG-OY",
   "localityName": "Irepo"
 },
 {
   "localityId": 100647,
   "regionId": "NG-OY",
   "localityName": "Iseyin"
 },
 {
   "localityId": 100648,
   "regionId": "NG-OY",
   "localityName": "Itesiwaju"
 },
 {
   "localityId": 100649,
   "regionId": "NG-OY",
   "localityName": "Iwajowa"
 },
 {
   "localityId": 100650,
   "regionId": "NG-OY",
   "localityName": "Kajola"
 },
 {
   "localityId": 100651,
   "regionId": "NG-OY",
   "localityName": "Lagelu"
 },
 {
   "localityId": 100652,
   "regionId": "NG-OY",
   "localityName": "Ogbomosho North"
 },
 {
   "localityId": 100653,
   "regionId": "NG-OY",
   "localityName": "Ogbomosho South"
 },
 {
   "localityId": 100654,
   "regionId": "NG-OY",
   "localityName": "Ogo Oluwa"
 },
 {
   "localityId": 100655,
   "regionId": "NG-OY",
   "localityName": "Olorunsogo"
 },
 {
   "localityId": 100656,
   "regionId": "NG-OY",
   "localityName": "Oluyole"
 },
 {
   "localityId": 100657,
   "regionId": "NG-OY",
   "localityName": "Ona-Ara"
 },
 {
   "localityId": 100658,
   "regionId": "NG-OY",
   "localityName": "Orelope"
 },
 {
   "localityId": 100659,
   "regionId": "NG-OY",
   "localityName": "Ori Ire"
 },
 {
   "localityId": 100660,
   "regionId": "NG-OY",
   "localityName": "Oyo East"
 },
 {
   "localityId": 100661,
   "regionId": "NG-OY",
   "localityName": "Oyo West"
 },
 {
   "localityId": 100662,
   "regionId": "NG-OY",
   "localityName": "Saki East"
 },
 {
   "localityId": 100663,
   "regionId": "NG-OY",
   "localityName": "Saki West"
 },
 {
   "localityId": 100664,
   "regionId": "NG-OY",
   "localityName": "Surulere"
 },
 {
   "localityId": 100665,
   "regionId": "NG-PL",
   "localityName": "Barkin Ladi"
 },
 {
   "localityId": 100666,
   "regionId": "NG-PL",
   "localityName": "Bassa"
 },
 {
   "localityId": 100667,
   "regionId": "NG-PL",
   "localityName": "Bokkos"
 },
 {
   "localityId": 100668,
   "regionId": "NG-PL",
   "localityName": "Jos East"
 },
 {
   "localityId": 100669,
   "regionId": "NG-PL",
   "localityName": "Jos North"
 },
 {
   "localityId": 100670,
   "regionId": "NG-PL",
   "localityName": "Jos South"
 },
 {
   "localityId": 100671,
   "regionId": "NG-PL",
   "localityName": "Kanam"
 },
 {
   "localityId": 100672,
   "regionId": "NG-PL",
   "localityName": "Kanke"
 },
 {
   "localityId": 100673,
   "regionId": "NG-PL",
   "localityName": "Langtang North"
 },
 {
   "localityId": 100674,
   "regionId": "NG-PL",
   "localityName": "Langtang South"
 },
 {
   "localityId": 100675,
   "regionId": "NG-PL",
   "localityName": "Mangu"
 },
 {
   "localityId": 100676,
   "regionId": "NG-PL",
   "localityName": "Mikang"
 },
 {
   "localityId": 100677,
   "regionId": "NG-PL",
   "localityName": "Pankshin"
 },
 {
   "localityId": 100678,
   "regionId": "NG-PL",
   "localityName": "Qua'an Pan"
 },
 {
   "localityId": 100679,
   "regionId": "NG-PL",
   "localityName": "Riyom"
 },
 {
   "localityId": 100680,
   "regionId": "NG-PL",
   "localityName": "Shendam"
 },
 {
   "localityId": 100681,
   "regionId": "NG-PL",
   "localityName": "Wase"
 },
 {
   "localityId": 100682,
   "regionId": "NG-RI",
   "localityName": "Abua - Odual"
 },
 {
   "localityId": 100683,
   "regionId": "NG-RI",
   "localityName": "Ahoada East"
 },
 {
   "localityId": 100684,
   "regionId": "NG-RI",
   "localityName": "Ahoada West"
 },
 {
   "localityId": 100685,
   "regionId": "NG-RI",
   "localityName": "Akuku Toru"
 },
 {
   "localityId": 100686,
   "regionId": "NG-RI",
   "localityName": "Andoni"
 },
 {
   "localityId": 100687,
   "regionId": "NG-RI",
   "localityName": "Asari-Toru"
 },
 {
   "localityId": 100688,
   "regionId": "NG-RI",
   "localityName": "Bonny"
 },
 {
   "localityId": 100689,
   "regionId": "NG-RI",
   "localityName": "Degema"
 },
 {
   "localityId": 100690,
   "regionId": "NG-RI",
   "localityName": "Eleme"
 },
 {
   "localityId": 100691,
   "regionId": "NG-RI",
   "localityName": "Emuoha"
 },
 {
   "localityId": 100692,
   "regionId": "NG-RI",
   "localityName": "Etche"
 },
 {
   "localityId": 100693,
   "regionId": "NG-RI",
   "localityName": "Gokana"
 },
 {
   "localityId": 100694,
   "regionId": "NG-RI",
   "localityName": "Ikwerre"
 },
 {
   "localityId": 100695,
   "regionId": "NG-RI",
   "localityName": "Khana"
 },
 {
   "localityId": 100696,
   "regionId": "NG-RI",
   "localityName": "Obio/Akpor"
 },
 {
   "localityId": 100697,
   "regionId": "NG-RI",
   "localityName": "Ogba - Egbema - Ndoni"
 },
 {
   "localityId": 100698,
   "regionId": "NG-RI",
   "localityName": "Ogu - Bolo"
 },
 {
   "localityId": 100699,
   "regionId": "NG-RI",
   "localityName": "Okrika"
 },
 {
   "localityId": 100700,
   "regionId": "NG-RI",
   "localityName": "Omumma"
 },
 {
   "localityId": 100701,
   "regionId": "NG-RI",
   "localityName": "Opobo - Nkoro"
 },
 {
   "localityId": 100702,
   "regionId": "NG-RI",
   "localityName": "Oyigbo"
 },
 {
   "localityId": 100703,
   "regionId": "NG-RI",
   "localityName": "Port-Harcourt"
 },
 {
   "localityId": 100704,
   "regionId": "NG-RI",
   "localityName": "Tai"
 },
 {
   "localityId": 100705,
   "regionId": "NG-SO",
   "localityName": "Binji"
 },
 {
   "localityId": 100706,
   "regionId": "NG-SO",
   "localityName": "Bodinga"
 },
 {
   "localityId": 100707,
   "regionId": "NG-SO",
   "localityName": "Dange Shuni"
 },
 {
   "localityId": 100708,
   "regionId": "NG-SO",
   "localityName": "Gada"
 },
 {
   "localityId": 100709,
   "regionId": "NG-SO",
   "localityName": "Goronyo"
 },
 {
   "localityId": 100710,
   "regionId": "NG-SO",
   "localityName": "Gudu"
 },
 {
   "localityId": 100711,
   "regionId": "NG-SO",
   "localityName": "Gwadabawa"
 },
 {
   "localityId": 100712,
   "regionId": "NG-SO",
   "localityName": "Illela"
 },
 {
   "localityId": 100713,
   "regionId": "NG-SO",
   "localityName": "Isa"
 },
 {
   "localityId": 100714,
   "regionId": "NG-SO",
   "localityName": "Kebbe"
 },
 {
   "localityId": 100715,
   "regionId": "NG-SO",
   "localityName": "Kware"
 },
 {
   "localityId": 100716,
   "regionId": "NG-SO",
   "localityName": "Rabah"
 },
 {
   "localityId": 100717,
   "regionId": "NG-SO",
   "localityName": "Sabon Birni"
 },
 {
   "localityId": 100718,
   "regionId": "NG-SO",
   "localityName": "Shagari"
 },
 {
   "localityId": 100719,
   "regionId": "NG-SO",
   "localityName": "Silame"
 },
 {
   "localityId": 100720,
   "regionId": "NG-SO",
   "localityName": "Sokoto North"
 },
 {
   "localityId": 100721,
   "regionId": "NG-SO",
   "localityName": "Sokoto South"
 },
 {
   "localityId": 100722,
   "regionId": "NG-SO",
   "localityName": "Tambuwal"
 },
 {
   "localityId": 100723,
   "regionId": "NG-SO",
   "localityName": "Tangaza"
 },
 {
   "localityId": 100724,
   "regionId": "NG-SO",
   "localityName": "Tureta"
 },
 {
   "localityId": 100725,
   "regionId": "NG-SO",
   "localityName": "Wamakko"
 },
 {
   "localityId": 100726,
   "regionId": "NG-SO",
   "localityName": "Wurno"
 },
 {
   "localityId": 100727,
   "regionId": "NG-SO",
   "localityName": "Yabo"
 },
 {
   "localityId": 100728,
   "regionId": "NG-TA",
   "localityName": "Ardo-Kola"
 },
 {
   "localityId": 100729,
   "regionId": "NG-TA",
   "localityName": "Bali"
 },
 {
   "localityId": 100730,
   "regionId": "NG-TA",
   "localityName": "Disputed Areas"
 },
 {
   "localityId": 100731,
   "regionId": "NG-TA",
   "localityName": "Donga"
 },
 {
   "localityId": 100732,
   "regionId": "NG-TA",
   "localityName": "Gashaka"
 },
 {
   "localityId": 100733,
   "regionId": "NG-TA",
   "localityName": "Gassol"
 },
 {
   "localityId": 100734,
   "regionId": "NG-TA",
   "localityName": "Ibi"
 },
 {
   "localityId": 100735,
   "regionId": "NG-TA",
   "localityName": "Jalingo"
 },
 {
   "localityId": 100736,
   "regionId": "NG-TA",
   "localityName": "Karim-Lamido"
 },
 {
   "localityId": 100737,
   "regionId": "NG-TA",
   "localityName": "Kurmi"
 },
 {
   "localityId": 100738,
   "regionId": "NG-TA",
   "localityName": "Lau"
 },
 {
   "localityId": 100739,
   "regionId": "NG-TA",
   "localityName": "Sardauna"
 },
 {
   "localityId": 100740,
   "regionId": "NG-TA",
   "localityName": "Takum"
 },
 {
   "localityId": 100741,
   "regionId": "NG-TA",
   "localityName": "Ussa"
 },
 {
   "localityId": 100742,
   "regionId": "NG-TA",
   "localityName": "Wukari"
 },
 {
   "localityId": 100743,
   "regionId": "NG-TA",
   "localityName": "Yorro"
 },
 {
   "localityId": 100744,
   "regionId": "NG-TA",
   "localityName": "Zing"
 },
 {
   "localityId": 100745,
   "regionId": "NG-YO",
   "localityName": "Bade"
 },
 {
   "localityId": 100746,
   "regionId": "NG-YO",
   "localityName": "Bursari"
 },
 {
   "localityId": 100747,
   "regionId": "NG-YO",
   "localityName": "Damaturu"
 },
 {
   "localityId": 100748,
   "regionId": "NG-YO",
   "localityName": "Fika"
 },
 {
   "localityId": 100749,
   "regionId": "NG-YO",
   "localityName": "Fune"
 },
 {
   "localityId": 100750,
   "regionId": "NG-YO",
   "localityName": "Geidam"
 },
 {
   "localityId": 100751,
   "regionId": "NG-YO",
   "localityName": "Gujba"
 },
 {
   "localityId": 100752,
   "regionId": "NG-YO",
   "localityName": "Gulani"
 },
 {
   "localityId": 100753,
   "regionId": "NG-YO",
   "localityName": "Jakusko"
 },
 {
   "localityId": 100754,
   "regionId": "NG-YO",
   "localityName": "Karasuwa"
 },
 {
   "localityId": 100755,
   "regionId": "NG-YO",
   "localityName": "Machina"
 },
 {
   "localityId": 100756,
   "regionId": "NG-YO",
   "localityName": "Nangere"
 },
 {
   "localityId": 100757,
   "regionId": "NG-YO",
   "localityName": "Nguru"
 },
 {
   "localityId": 100758,
   "regionId": "NG-YO",
   "localityName": "Potiskum"
 },
 {
   "localityId": 100759,
   "regionId": "NG-YO",
   "localityName": "Tarmua"
 },
 {
   "localityId": 100760,
   "regionId": "NG-YO",
   "localityName": "Yunusari"
 },
 {
   "localityId": 100761,
   "regionId": "NG-YO",
   "localityName": "Yusufari"
 },
 {
   "localityId": 100762,
   "regionId": "NG-ZA",
   "localityName": "Anka"
 },
 {
   "localityId": 100763,
   "regionId": "NG-ZA",
   "localityName": "Bakura"
 },
 {
   "localityId": 100764,
   "regionId": "NG-ZA",
   "localityName": "Birnin Magaji"
 },
 {
   "localityId": 100765,
   "regionId": "NG-ZA",
   "localityName": "Bukkuyum"
 },
 {
   "localityId": 100766,
   "regionId": "NG-ZA",
   "localityName": "Bungudu"
 },
 {
   "localityId": 100767,
   "regionId": "NG-ZA",
   "localityName": "Gummi"
 },
 {
   "localityId": 100768,
   "regionId": "NG-ZA",
   "localityName": "Gusau"
 },
 {
   "localityId": 100769,
   "regionId": "NG-ZA",
   "localityName": "Kaura Namoda"
 },
 {
   "localityId": 100770,
   "regionId": "NG-ZA",
   "localityName": "Maradun"
 },
 {
   "localityId": 100771,
   "regionId": "NG-ZA",
   "localityName": "Maru"
 },
 {
   "localityId": 100772,
   "regionId": "NG-ZA",
   "localityName": "Shinkafi"
 },
 {
   "localityId": 100773,
   "regionId": "NG-ZA",
   "localityName": "Talata Mafara"
 },
 {
   "localityId": 100774,
   "regionId": "NG-ZA",
   "localityName": "Tsafe"
 },
 {
   "localityId": 100775,
   "regionId": "NG-ZA",
   "localityName": "Zurmi"
 }
]